nBodyEngine/Body.py
nBodyEngine/GraphEngine.py
nBodyEngine/__init__.py
nBodyEngine-1.0.0.dist-info/LICENSE
nBodyEngine-1.0.0.dist-info/METADATA
nBodyEngine-1.0.0.dist-info/WHEEL
nBodyEngine-1.0.0.dist-info/top_level.txt
nBodyEngine-1.0.0.dist-info/RECORD
