Metadata-Version: 2.1
Name: nBodyEngine
Version: 1.0.0
Summary: A lightweight engine to simulate the n-Body problem with Newtonian and post-Newtonian mechanics
Author: Federico B.
License-File: LICENSE
Requires-Dist: numpy
Requires-Dist: matplotlib
